librunner/__init__.py
librunner/controller.py
librunner/main.py
librunner/model.py
librunner/runner.py
librunner-0.0.2.dist-info/LICENSE
librunner-0.0.2.dist-info/METADATA
librunner-0.0.2.dist-info/WHEEL
librunner-0.0.2.dist-info/top_level.txt
librunner-0.0.2.dist-info/RECORD
