Metadata-Version: 2.1
Name: librunner
Version: 0.0.2
Summary: A package to run python models in parallel
Home-page: https://github.com/alex-van-vliet/librunner
Author: Alex van Vliet
Author-email: alex@vanvliet.pro
License: UNKNOWN
Platform: UNKNOWN
Classifier: Programming Language :: Python :: 3
Classifier: License :: OSI Approved :: MIT License
Classifier: Operating System :: OS Independent
Requires-Python: >=3.8
